<?xml version="1.0" encoding="utf-8"?>
<!-- S4TK Type: E882D22F, Group: 00000000, Instance: 0000000016DE3AE0 -->
<I c="Big3UniverseAssignSunImmediate" i="interaction" m="plumantics_big3_runtime.integration.interactions" n="PlumAntics_Big3Mod_LetTheHeavensDecide" s="383662816">
  <T n="allow_autonomous">False</T>
  <T n="allow_user_directed">True</T>
  <T n="category">3724778905<!--PlumAntics_Big3Mod_Discover_Natal_PieMenu--></T>
  <T n="display_name">0xF0F99E4E<!--display_name--></T>
  <V n="display_tooltip" t="enabled">
    <T n="enabled">0xA53F1E60<!--Assigns a Sun sign at random if your Sim has no Big 3 signs yet. Let the stars spin the wheel and hope they had coffee.--></T>
  </V>
  <T n="pie_menu_priority">5</T>
  <U n="progress_bar_enabled">
    <T n="bar_enabled">False</T>
  </U>
  <E n="target_type">TARGET</E>
  <L n="tests">
    <L>
      <V t="sim_info">
        <U n="sim_info">
          <V n="ages" t="specified">
            <L n="specified">
              <E>ADULT</E>
              <E>TEEN</E>
              <E>YOUNGADULT</E>
              <E>ELDER</E>
            </L>
          </V>
        </U>
      </V>
      <!-- AND block -->
      <!-- Must NOT already have ANY Sun -->
      <V t="trait">
        <U n="trait">
          <E n="subject">Actor</E>
          <L n="blacklist_traits">
            <T>3164395998<!--PlumAntics_Big3Mod_AriesSun--></T>
            <T>4281780916<!--PlumAntics_Big3Mod_TaurusSun--></T>
            <T>3771207495<!--PlumAntics_Big3Mod_GeminiSun--></T>
            <T>2654235180<!--PlumAntics_Big3Mod_CancerSun--></T>
            <T>2797810424<!--PlumAntics_Big3Mod_LeoSun--></T>
            <T>3413939915<!--PlumAntics_Big3Mod_VirgoSun--></T>
            <T>3887839626<!--PlumAntics_Big3Mod_LibraSun--></T>
            <T>2636947797<!--PlumAntics_Big3Mod_ScorpioSun--></T>
            <T>3298769274<!--PlumAntics_Big3Mod_SagittariusSun--></T>
            <T>3356986463<!--PlumAntics_Big3Mod_CapricornSun--></T>
            <T>4169897889<!--PlumAntics_Big3Mod_AquariusSun--></T>
            <T>2363848465<!--PlumAntics_Big3Mod_PiscesSun--></T>
          </L>
        </U>
      </V>
      <!-- Must NOT already have ANY Moon -->
      <V t="trait">
        <U n="trait">
          <E n="subject">Actor</E>
          <L n="blacklist_traits">
            <T>2620839130<!--Scorpio Moon--></T>
            <T>4264462837<!--Cancer Moon--></T>
            <T>2174778494<!--Pisces Moon--></T>
            <T>4080273607<!--PlumAntics_Big3Mod_AriesMoon--></T>
            <T>3468113049<!--Leo Moon--></T>
            <T>3557938955<!--Sag Moon--></T>
            <T>2968393124<!--Gemini Moon--></T>
            <T>2266439355<!--Libra Moon--></T>
            <T>2783528558<!--Aquarius Moon--></T>
            <T>3434935389<!--Taurus Moon--></T>
            <T>3315030320<!--Virgo Moon--></T>
            <T>4251664764<!--Cap Moon--></T>
          </L>
        </U>
      </V>
      <!-- Must NOT already have ANY Rising -->
      <V t="trait">
        <U n="trait">
          <E n="subject">Actor</E>
          <L n="blacklist_traits">
            <T>2297406366<!--Aries Rising--></T>
            <T>2588878312<!--Taurus Rising--></T>
            <T>4242808797<!--Gemini Rising--></T>
            <T>2154635568<!--Cancer Rising--></T>
            <T>3739357428<!--Leo Rising--></T>
            <T>2665561705<!--Virgo Rising--></T>
            <T>3123976786<!--Libra Rising--></T>
            <T>3923158167<!--Scorpio Rising--></T>
            <T>2405249506<!--Sag Rising--></T>
            <T>3178572581<!--Cap Rising--></T>
            <T>2243949835<!--Aquarius Rising--></T>
            <T>3588503643<!--Pisces Rising--></T>
          </L>
        </U>
      </V>
    </L>
  </L>
  <V n="outcome" t="single">
    <U n="single">
      <U n="actions">
        <L n="loot_list" />
      </U>
    </U>
  </V>
</I>
