<?xml version="1.0" encoding="utf-8"?>
<!-- S4TK Type: 0C772E27, Group: 00000000, Instance: 8F897D54707C6545 -->
<I c="LootActions" i="action" m="interactions.utils.loot" n="PlumAntics_Big3Mod_SagSunBuffsLoot" s="10342935820850980165">
  <L n="loot_actions">
    <V t="actions">
      <T n="actions">17618495096311993492<!--PlumAntics_Big3Mod_AddSagSun--></T>
    </V>
  </L>
  <T n="run_test_first">True</T>
  <L n="tests">
    <L>
      <V t="trait">
        <U n="trait">
          <L n="whitelist_traits">
            <T>3298769274<!--PlumAntics_Big3Mod_SagittariusSun--></T>
          </L>
        </U>
      </V>
    </L>
  </L>
</I>