<?xml version="1.0" encoding="utf-8"?>
<I c="LootActions" s="2320707984" i="action" m="interactions.utils.loot" n="PlumAntics_Big3Mod_RemoveElementsfromAriesSun">
  <L n="loot_actions">
    <V t="trait_remove">
      <U n="trait_remove">
        <V n="trait" t="specific_trait">
          <U n="specific_trait">
            <T n="specific_trait">3858955547<!--PlumAntics_Big3Mod_Mars--></T>
          </U>
        </V>
      </U>
    </V>
    <V t="trait_remove">
      <U n="trait_remove">
        <V n="trait" t="specific_trait">
          <U n="specific_trait">
            <T n="specific_trait">3493848740<!--PlumAntics_Big3Mod_Cardinal--></T>
          </U>
        </V>
      </U>
    </V>
    <V t="trait_remove">
      <U n="trait_remove">
        <V n="trait" t="specific_trait">
          <U n="specific_trait">
            <T n="specific_trait">2913211980<!--PlumAntics_Big3Mod_ElementFire--></T>
          </U>
        </V>
      </U>
    </V>
    </L>
</I>